vta/__init__.py
vta/vta.py
vta-0.1.dist-info/LICENSE
vta-0.1.dist-info/METADATA
vta-0.1.dist-info/WHEEL
vta-0.1.dist-info/top_level.txt
vta-0.1.dist-info/RECORD
