Metadata-Version: 2.1
Name: vta
Version: 0.1
Summary: These package provides VirusTotal API module
Home-page: https://github.com/woodonggyu
Author: WOODONGGYU
Author-email: mrwoo92@naver.com
License: WOODONGGYU
Platform: UNKNOWN
Classifier: Programming Language :: Python :: 3
